src/__init__.py
src/Gaosong/__init__.py
src/Gaosong/analise/__init__.py
src/Gaosong/analise/score_analysis.py
src/Gaosong/analise/work_consumption.py
src/Gaosong/game/__init__.py
src/Gaosong/game/game.py
src/Gaosong/resource/__init__.py
src/Suyongfan/__init__.py
src/Suyongfan/resource/__init__.py
Fianl_code-0.0.1.dist-info/METADATA
Fianl_code-0.0.1.dist-info/WHEEL
Fianl_code-0.0.1.dist-info/top_level.txt
Fianl_code-0.0.1.dist-info/RECORD
